fmpict/__init__.py
fmpict/fmpict.py
fmpict-0.0.5.dist-info/DESCRIPTION.rst
fmpict-0.0.5.dist-info/METADATA
fmpict-0.0.5.dist-info/RECORD
fmpict-0.0.5.dist-info/WHEEL
fmpict-0.0.5.dist-info/entry_points.txt
fmpict-0.0.5.dist-info/metadata.json
fmpict-0.0.5.dist-info/top_level.txt
