Metadata-Version: 2.0
Name: fmpict
Version: 0.0.5
Summary: Combinatorial testing tool using FreeMind and PICT
Home-page: https://github.com/hiro-iseri/fmpict
Author: Hiroki Iseri
Author-email: iseri.hiroki@gmail.com
License: MIT
Keywords: Combinatorial testing tool
Platform: UNKNOWN
Classifier: Development Status :: 3 - Alpha
Classifier: Intended Audience :: Developers
Classifier: Topic :: Software Development :: Testing
Classifier: License :: OSI Approved :: MIT License
Classifier: Programming Language :: Python :: 2.7
Classifier: Programming Language :: Python :: 3
Classifier: Programming Language :: Python :: 3.4
Classifier: Programming Language :: Python :: 3.5
Classifier: Programming Language :: Python :: 3.6
Classifier: Programming Language :: Python :: 3.7
